rodin/__init__.py
rodin/rodin.py
rodin/mummichog/JSON_metabolicModels.py
rodin/mummichog/__init__.py
rodin/mummichog/compound_dicts.py
rodin/mummichog/config.py
rodin/mummichog/functional_analysis.py
rodin/mummichog/get_user_data.py
rodin/mummichog/ions.py
rodin/mummichog/models.py
rodin-1.9.12.dist-info/licenses/LICENSE
rodin-1.9.12.dist-info/METADATA
rodin-1.9.12.dist-info/WHEEL
rodin-1.9.12.dist-info/top_level.txt
rodin-1.9.12.dist-info/RECORD
