Metadata-Version: 2.4
Name: rodin
Version: 1.9.12
Summary: A comprehensive toolkit for processing and analyzing metabolomics data.
Home-page: https://github.com/BM-Boris/rodin
Author: Boris Minasenko
Author-email: boris.minasenko@emory.edu
Classifier: Programming Language :: Python :: 3
Classifier: License :: OSI Approved :: MIT License
Classifier: Operating System :: OS Independent
Requires-Python: >=3.10
License-File: LICENSE
Requires-Dist: numpy>=1.21.4
Requires-Dist: pandas>=1.3.4
Requires-Dist: scipy>=1.7.3
Requires-Dist: scikit-learn>=1.0
Requires-Dist: umap-learn>=0.5.1
Requires-Dist: matplotlib>=3.5.0
Requires-Dist: seaborn>=0.11.2
Requires-Dist: statsmodels>=0.13.0
Requires-Dist: tqdm>=4.62.3
Requires-Dist: dash-bio>=0.8.0
Requires-Dist: dash>=2.7.0
Requires-Dist: pickle-mixin>=1.0.2
Requires-Dist: networkx>=2.6
Requires-Dist: plotly>=5.19.0
Requires-Dist: fastcluster
Dynamic: author
Dynamic: author-email
Dynamic: classifier
Dynamic: description
Dynamic: description-content-type
Dynamic: home-page
Dynamic: license-file
Dynamic: requires-dist
Dynamic: requires-python
Dynamic: summary
